HuoyongPaoxueSiwei/README.md
HuoyongPaoxueSiwei/__init__.py
HuoyongPaoxueSiwei/__main__.py
HuoyongPaoxueSiwei/file.epub
HuoyongPaoxueSiwei/index.html
HuoyongPaoxueSiwei/css/__init__.py
HuoyongPaoxueSiwei/css/annotations.css
HuoyongPaoxueSiwei/css/main.css
HuoyongPaoxueSiwei/css/normalize.css
HuoyongPaoxueSiwei/css/popup.css
HuoyongPaoxueSiwei/font/__init__.py
HuoyongPaoxueSiwei/font/fontello.eot
HuoyongPaoxueSiwei/font/fontello.svg
HuoyongPaoxueSiwei/font/fontello.ttf
HuoyongPaoxueSiwei/font/fontello.woff
HuoyongPaoxueSiwei/img/__init__.py
HuoyongPaoxueSiwei/img/annotator-glyph-sprite.png
HuoyongPaoxueSiwei/img/annotator-icon-sprite.png
HuoyongPaoxueSiwei/img/apple-touch-icon.png
HuoyongPaoxueSiwei/img/cancelfullscreen.png
HuoyongPaoxueSiwei/img/close.png
HuoyongPaoxueSiwei/img/fullscreen.png
HuoyongPaoxueSiwei/img/loader.gif
HuoyongPaoxueSiwei/img/menu-icon.png
HuoyongPaoxueSiwei/img/save.png
HuoyongPaoxueSiwei/img/saved.png
HuoyongPaoxueSiwei/img/settings-s.png
HuoyongPaoxueSiwei/img/settings.png
HuoyongPaoxueSiwei/img/star.png
HuoyongPaoxueSiwei/js/__init__.py
HuoyongPaoxueSiwei/js/epub.js
HuoyongPaoxueSiwei/js/epub.min.js
HuoyongPaoxueSiwei/js/epub.min.map
HuoyongPaoxueSiwei/js/hooks.min.js
HuoyongPaoxueSiwei/js/hooks.min.map
HuoyongPaoxueSiwei/js/reader.js
HuoyongPaoxueSiwei/js/reader.js.map
HuoyongPaoxueSiwei/js/reader.min.js
HuoyongPaoxueSiwei/js/reader.min.map
HuoyongPaoxueSiwei/js/hooks/__init__.py
HuoyongPaoxueSiwei/js/hooks/extensions/__init__.py
HuoyongPaoxueSiwei/js/hooks/extensions/highlight.js
HuoyongPaoxueSiwei/js/libs/__init__.py
HuoyongPaoxueSiwei/js/libs/jquery.min.js
HuoyongPaoxueSiwei/js/libs/localforage.min.js
HuoyongPaoxueSiwei/js/libs/screenfull.js
HuoyongPaoxueSiwei/js/libs/screenfull.min.js
HuoyongPaoxueSiwei/js/libs/zip.min.js
HuoyongPaoxueSiwei/js/plugins/__init__.py
HuoyongPaoxueSiwei/js/plugins/hypothesis.js
HuoyongPaoxueSiwei/js/plugins/search.js
huoyong_paoxue_siwei-2022.10.11.0.dist-info/METADATA
huoyong_paoxue_siwei-2022.10.11.0.dist-info/WHEEL
huoyong_paoxue_siwei-2022.10.11.0.dist-info/entry_points.txt
huoyong_paoxue_siwei-2022.10.11.0.dist-info/top_level.txt
huoyong_paoxue_siwei-2022.10.11.0.dist-info/RECORD
